{
  "url": "https://xq-booking-uat.newshore.es/",
  "slug": "xq-booking-uat-newshore-es",
  "updatedAt": "2026-07-09T10:45:15Z",
  "series": {
    "mobile": [
      {
        "t": "2026-07-08T10:17:41Z",
        "score": 47,
        "lcp": 6423.171654466769,
        "cls": 0,
        "tbt": 478
      },
      {
        "t": "2026-07-08T12:13:48Z",
        "score": 54,
        "fcp": 4585.56905964061,
        "lcp": 11002.878932078114,
        "tbt": 193.5,
        "cls": 0,
        "si": 10773.117627390428
      },
      {
        "t": "2026-07-08T15:09:03Z",
        "score": 56,
        "fcp": 4438.847499539929,
        "lcp": 17692.156579859,
        "tbt": 108,
        "cls": 0,
        "si": 13404.49267731594
      },
      {
        "t": "2026-07-08T17:19:05Z",
        "score": 38,
        "fcp": 4549.195885223444,
        "lcp": 17867.508582730792,
        "tbt": 770,
        "cls": 0,
        "si": 12723.662349810558
      },
      {
        "t": "2026-07-08T17:33:53Z",
        "score": 48,
        "fcp": 4406.902877836946,
        "lcp": 17527.26686101825,
        "tbt": 372.5,
        "cls": 0,
        "si": 11601.37986606715
      },
      {
        "t": "2026-07-08T19:06:48Z",
        "score": 61,
        "fcp": 3193.180962501457,
        "lcp": 10870.482490295319,
        "tbt": 136.49999999999818,
        "cls": 0.059714,
        "si": 7235.585843037012
      },
      {
        "t": "2026-07-08T20:56:24Z",
        "score": 40,
        "fcp": 3248.117908377388,
        "lcp": 10861.419946899026,
        "tbt": 806.5,
        "cls": 0.083064,
        "si": 9819.16318353018
      },
      {
        "t": "2026-07-08T22:00:38Z",
        "score": 42,
        "fcp": 3303.6619707241252,
        "lcp": 10796.478070200152,
        "tbt": 719,
        "cls": 0.041867,
        "si": 10811.29379024109
      },
      {
        "t": "2026-07-08T23:59:28Z",
        "score": 47,
        "fcp": 3239.3492959277464,
        "lcp": 10381.650824881672,
        "tbt": 477.5,
        "cls": 0.029683,
        "si": 13270.25246280088
      },
      {
        "t": "2026-07-09T03:31:57Z",
        "score": 46,
        "fcp": 3252.97952343233,
        "lcp": 10587.789736402687,
        "tbt": 512,
        "cls": 0.053726,
        "si": 10898.28393847004
      },
      {
        "t": "2026-07-09T07:28:37Z",
        "score": 48,
        "fcp": 3279.5481637085695,
        "lcp": 10221.866126606868,
        "tbt": 456,
        "cls": 0.043899999999999995,
        "si": 11154.913400072834
      },
      {
        "t": "2026-07-09T08:33:02Z",
        "score": 42,
        "fcp": 3242.398654608028,
        "lcp": 10140.704777557858,
        "tbt": 727.5,
        "cls": 0.083064,
        "si": 7740.834029829282
      },
      {
        "t": "2026-07-09T10:26:55Z",
        "score": 46,
        "fcp": 3212.6506653538117,
        "lcp": 8698.96011694648,
        "tbt": 663.4999999999982,
        "cls": 0,
        "si": 7614.912162236112
      },
      {
        "t": "2026-07-09T10:45:15Z",
        "score": 51,
        "fcp": 3240.061762605613,
        "lcp": 11261.363532281479,
        "tbt": 369,
        "cls": 0.046228,
        "si": 9930.29972344646
      }
    ],
    "desktop": [
      {
        "t": "2026-07-08T10:17:41Z",
        "score": 29,
        "lcp": 8917.832356555977,
        "cls": 0,
        "tbt": 4649.161344449993
      },
      {
        "t": "2026-07-08T12:13:48Z",
        "score": 66,
        "fcp": 1037.940466780282,
        "lcp": 3478.251622942714,
        "tbt": 206.99999999999955,
        "cls": 0,
        "si": 2665.1513991994716
      },
      {
        "t": "2026-07-08T15:09:03Z",
        "score": 73,
        "fcp": 1019.0499408411868,
        "lcp": 3261.370848831055,
        "tbt": 118.00000000000045,
        "cls": 0,
        "si": 2586.4989817215305
      },
      {
        "t": "2026-07-08T17:19:05Z",
        "score": 37,
        "fcp": 1223.389254905881,
        "lcp": 4215.242897541464,
        "tbt": 1076.8587034411808,
        "cls": 0,
        "si": 5938.257048318604
      },
      {
        "t": "2026-07-08T17:33:53Z",
        "score": 52,
        "fcp": 1015.2921910055417,
        "lcp": 3690.591729580955,
        "tbt": 398,
        "cls": 0,
        "si": 4123.966580058642
      },
      {
        "t": "2026-07-08T19:06:48Z",
        "score": 48,
        "fcp": 805.5529320606624,
        "lcp": 2856.212166913334,
        "tbt": 769.9999999999995,
        "cls": 0.014898,
        "si": 3903.05905266609
      },
      {
        "t": "2026-07-08T20:56:24Z",
        "score": 61,
        "fcp": 762.16415974608,
        "lcp": 2143.82673235011,
        "tbt": 499.3003974891153,
        "cls": 0.014898,
        "si": 2954.8755999959767
      },
      {
        "t": "2026-07-08T22:00:38Z",
        "score": 71,
        "fcp": 745.9149833015783,
        "lcp": 2209.216002539675,
        "tbt": 257.2182694242467,
        "cls": 0.014898,
        "si": 3020.248632204154
      },
      {
        "t": "2026-07-08T23:59:28Z",
        "score": 47,
        "fcp": 825.4092198168479,
        "lcp": 2542.721191045727,
        "tbt": 1207.9544309101166,
        "cls": 0.01539,
        "si": 6327.782452668664
      },
      {
        "t": "2026-07-09T03:31:57Z",
        "score": 78,
        "fcp": 745.7925242038617,
        "lcp": 2266.5965979706552,
        "tbt": 151.50000000000045,
        "cls": 0.014898,
        "si": 2989.2763389427228
      },
      {
        "t": "2026-07-09T07:28:37Z",
        "score": 82,
        "fcp": 738.6481482037884,
        "lcp": 2157.9563904055035,
        "tbt": 37,
        "cls": 0.014898,
        "si": 2958.089938364509
      },
      {
        "t": "2026-07-09T08:33:02Z",
        "score": 67,
        "fcp": 772.5903676655125,
        "lcp": 1968.896610747107,
        "tbt": 413,
        "cls": 0.014898,
        "si": 2350.6413009214157
      },
      {
        "t": "2026-07-09T10:26:55Z",
        "score": 52,
        "fcp": 789.6818880203526,
        "lcp": 2288.39371444121,
        "tbt": 827.9999999999998,
        "cls": 0.014898,
        "si": 3668.783109519851
      },
      {
        "t": "2026-07-09T10:45:15Z",
        "score": 64,
        "fcp": 798.2674522960543,
        "lcp": 1945.2770333215626,
        "tbt": 467,
        "cls": 0.014898,
        "si": 2612.288761804345
      }
    ]
  },
  "thresholds": {
    "mobile": 50,
    "desktop": 66
  },
  "label": "UAT Environment"
}